LICENSE.txt
README.md
setup.cfg
setup.py
oahspe/SSL.py
oahspe/crypt.py
oahspe/execute.py
oahspe/host.py
oahspe/tool.py
oahspe.egg-info/PKG-INFO
oahspe.egg-info/SOURCES.txt
oahspe.egg-info/dependency_links.txt
oahspe.egg-info/top_level.txt