Metadata-Version: 2.1
Name: oahspe
Version: 0.0.17
Summary: Cloud DevOps
Home-page: https://github.com/quangproo/oahspe
Download-URL: https://github.com/user/reponame/archive/v_01.tar.gz
Author: quangproo
Author-email: contact@quang.pro
License: MIT
Keywords: oahspe
Classifier: Development Status :: 5 - Production/Stable
Classifier: Intended Audience :: Developers
Classifier: Topic :: Software Development :: Build Tools
Classifier: License :: OSI Approved :: MIT License
Classifier: Programming Language :: Python :: 3
License-File: LICENSE.txt
